{
  "data": [
    {
      "img": "exit",
      "name": "浙F.37554",
      "men": "南门",
      "date": "08:05:12"
    },
    {
      "img": "enter",
      "name": "浙F.37554",
      "men": "南门",
      "date": "08:05:12"
    },
    {
      "img": "exit",
      "name": "浙F.37554",
      "men": "南门",
      "date": "08:05:12"
    },
    {
      "img": "exit",
      "name": "浙A.37554",
      "men": "南门",
      "date": "08:05:12"
    },
    {
      "img": "exit",
      "name": "浙A.37554",
      "men": "南门",
      "date": "08:05:12"
    },
    {
      "img": "exit",
      "name": "浙A.37554",
      "men": "南门",
      "date": "08:05:12"
    },{
      "img": "exit",
      "name": "浙A.37554",
      "men": "南门",
      "date": "08:05:12"
    }
  ]
}
